mpb_lib/__init__.py
mpb_lib/apis/__init__.py
mpb_lib/cannon/__init__.py
mpb_lib/cannon/cannon.py
mpb_lib/cannon/cannon_html.py
mpb_lib/face/__init__.py
mpb_lib/face/face.py
mpb_lib/face/face_html.py
mpb_lib/maze/__init__.py
mpb_lib/rpg/__init__.py
mpb_lib/rpg/rpg.py
mpb_lib/rpg/rpg_html.py
mpb_lib/rythmbox/__init__.py
mpb_lib/rythmbox/rythmbox.py
mpb_lib/rythmbox/rythmbox_html.py
mpb_lib/sound/__init__.py
mpb_lib/sound/wavs/a.wav
mpb_lib/sound/wavs/b.wav
mpb_lib/sound/wavs/c.wav
mpb_lib/sound/wavs/d.wav
mpb_lib/sound/wavs/e.wav
mpb_lib/sound/wavs/f.wav
mpb_lib/sound/wavs/g.wav
mpb_lib/sugoi/__init__.py
mpb_lib/tictactoe/__init__.py
mpb_lib/tictactoe/tictactoe.py
mpb_lib/tictactoe/tictactoe_html.py
mpb_lib/vowelgen/HPF.py
mpb_lib/vowelgen/__init__.py
mpb_lib/vowelgen/glottal.py
mpb_lib/vowelgen/threetube.py
mpb_lib/vowelgen/twotube.py
mpb_lib-0.1.89.dist-info/METADATA
mpb_lib-0.1.89.dist-info/WHEEL
mpb_lib-0.1.89.dist-info/top_level.txt
mpb_lib-0.1.89.dist-info/RECORD
