Metadata-Version: 2.1
Name: mpb-lib
Version: 0.1.89
Summary: A library for minpro.
Home-page: 
Author: Atsushi Shibata
Author-email: shibata@m-info.co.jp
License: MIT
Platform: UNKNOWN
Classifier: License :: OSI Approved :: MIT License
Classifier: Programming Language :: Python :: 3.6
